gsheets/__init__.py
gsheets/admin.py
gsheets/apps.py
gsheets/auth.py
gsheets/decorators.py
gsheets/gsheets.py
gsheets/mixins.py
gsheets/models.py
gsheets/settings.py
gsheets/tests.py
gsheets/urls.py
gsheets/views.py
gsheets/management/__init__.py
gsheets/management/commands/__init__.py
gsheets/management/commands/syncgsheets.py
gsheets/migrations/0001_initial.py
gsheets/migrations/0002_accesscredentials_created_time.py
gsheets/migrations/__init__.py
gsheets/signals/__init__.py
django_gsheets-0.0.10.dist-info/LICENSE
django_gsheets-0.0.10.dist-info/METADATA
django_gsheets-0.0.10.dist-info/WHEEL
django_gsheets-0.0.10.dist-info/top_level.txt
django_gsheets-0.0.10.dist-info/RECORD
